pyfrdas2/__init__.py
pyfrdas2/fantoir.py
pyfrdas2/pyfrdas2.py
pyfrdas2/pgp_keys/2022-DGFIP_TIERSDECLARANTS_PROD.asc
pyfrdas2/pgp_keys/2022-DGFIP_TIERSDECLARANTS_TEST.asc
pyfrdas2/pgp_keys/2023-DGFIP_TIERSDECLARANTS_PROD.asc
pyfrdas2/pgp_keys/2023-DGFIP_TIERSDECLARANTS_TEST.asc
pyfrdas2-0.9.dist-info/METADATA
pyfrdas2-0.9.dist-info/WHEEL
pyfrdas2-0.9.dist-info/RECORD
