Metadata-Version: 2.1
Name: pyfrdas2
Version: 0.9
Summary: Generate DAS2 for the french tax administration
Project-URL: Homepage, https://github.com/akretion/pyfrdas2
Project-URL: Source, https://github.com/akretion/pyfrdas2
Project-URL: Issues, https://github.com/akretion/pyfrdas2/issues
Author-email: Alexis de Lattre <alexis.delattre@akretion.com>
Classifier: Development Status :: 5 - Production/Stable
Classifier: Intended Audience :: Developers
Classifier: License :: OSI Approved :: GNU Lesser General Public License v2 or later (LGPLv2+)
Classifier: Operating System :: OS Independent
Classifier: Programming Language :: Python :: 3
Classifier: Topic :: Office/Business :: Financial :: Accounting
Requires-Python: >=3.7
Requires-Dist: python-gnupg
Requires-Dist: unidecode
